dynapipeline/__init__.py
dynapipeline/config/__init__.py
dynapipeline/contexts/__init__.py
dynapipeline/contexts/async_ctx.py
dynapipeline/contexts/protected.py
dynapipeline/core/__init__.py
dynapipeline/core/base_stage.py
dynapipeline/core/component.py
dynapipeline/core/context.py
dynapipeline/core/handler.py
dynapipeline/core/handler_registry.py
dynapipeline/errors/__init__.py
dynapipeline/errors/base.py
dynapipeline/errors/pipeline.py
dynapipeline/errors/stage.py
dynapipeline/exceptions/__init__.py
dynapipeline/exceptions/base.py
dynapipeline/exceptions/context.py
dynapipeline/exceptions/registry.py
dynapipeline/execution/__init__.py
dynapipeline/execution/base.py
dynapipeline/execution/cycle_strategies.py
dynapipeline/execution/strategies.py
dynapipeline/handlers/__init__.py
dynapipeline/handlers/handler.py
dynapipeline/handlers/handler_registry.py
dynapipeline/pipelines/__init__.py
dynapipeline/pipelines/component.py
dynapipeline/pipelines/factory.py
dynapipeline/pipelines/pipeline.py
dynapipeline/pipelines/stage.py
dynapipeline/pipelines/stage_group.py
dynapipeline/plugins/__init__.py
dynapipeline/utils/__init__.py
dynapipeline/utils/base_registry.py
dynapipeline/utils/error_levels.py
dynapipeline/utils/handler_types.py
dynapipeline/utils/list_registry.py
dynapipeline/utils/pipeline_types.py
dynapipeline/utils/timer.py
dynapipeline/utils/types.py
dynapipeline-0.1.0.dist-info/LICENSE
dynapipeline-0.1.0.dist-info/METADATA
dynapipeline-0.1.0.dist-info/WHEEL
dynapipeline-0.1.0.dist-info/top_level.txt
dynapipeline-0.1.0.dist-info/RECORD
