Metadata-Version: 2.1
Name: dynapipeline
Version: 0.1.0
Summary: A flexible, event-driven pipeline framework for data processing
Home-page: https://github.com/oldcorvus/dynapipeline
Author: Moel
Author-email: mohana.rj13@example.com
Classifier: Programming Language :: Python :: 3.11
Classifier: License :: OSI Approved :: MIT License
Classifier: Operating System :: OS Independent
Requires-Python: >=3.11
License-File: LICENSE
Requires-Dist: pydantic>=1.8.2
Provides-Extra: dev
Requires-Dist: pytest; extra == "dev"
Requires-Dist: tox; extra == "dev"
Requires-Dist: flake8; extra == "dev"
